tests/__init__.py
tests/test_classdict.py
tests/test_metaclass.py
jx_enum-1.0.0.dist-info/LICENSE
jx_enum-1.0.0.dist-info/METADATA
jx_enum-1.0.0.dist-info/WHEEL
jx_enum-1.0.0.dist-info/top_level.txt
jx_enum-1.0.0.dist-info/RECORD
