Metadata-Version: 2.1
Name: jx-enum
Version: 1.0.0
Summary: A small enum package
Home-page: https://gitlab.com/jiao.xue.libs/enum
Author: Xue Jiao
Author-email: jiao.xuejiao@gmail.com
License: UNKNOWN
Platform: UNKNOWN
Classifier: Programming Language :: Python :: 2
Classifier: License :: OSI Approved :: MIT License
Classifier: Operating System :: OS Independent
Requires-Dist: six
